pydifact/__init__.py
pydifact/api.py
pydifact/parser.py
pydifact/segmentcollection.py
pydifact/segments.py
pydifact/serializer.py
pydifact/token.py
pydifact/tokenizer.py
pydifact/control/__init__.py
pydifact/control/characters.py
pydifact/syntax/__init__.py
pydifact/syntax/common.py
pydifact/syntax/v1.py
pydifact/syntax/v3.py
pydifact/syntax/v4.py
pydifact-0.1.7.dist-info/LICENSE
pydifact-0.1.7.dist-info/METADATA
pydifact-0.1.7.dist-info/WHEEL
pydifact-0.1.7.dist-info/top_level.txt
pydifact-0.1.7.dist-info/RECORD
