Metadata-Version: 2.1
Name: pydifact
Version: 0.1.7
Summary: Pydifact is a library that aims to provide complete support for reading and writing EDIFACT files. These file format, despite being old, is still a standard in many business cases. In Austria e.g., it is used for the transfer of medical reports between medical doctors.
Author-email: Christian González <christian.gonzalez@nerdocs.at>
License: MIT License
Project-URL: Documentation, https://pydifact.readthedocs.io
Project-URL: Repository, https://github.com/nerdocs/pydifact
Project-URL: Issues, https://github.com/nerdocs/pydifact/issues
Classifier: Development Status :: 3 - Alpha
Classifier: Environment :: Console
Classifier: Intended Audience :: Developers
Classifier: License :: OSI Approved :: MIT License
Classifier: Natural Language :: English
Classifier: Operating System :: MacOS :: MacOS X
Classifier: Operating System :: Microsoft :: Windows
Classifier: Operating System :: POSIX
Classifier: Programming Language :: Python :: 3
Classifier: Topic :: Software Development :: Libraries
Requires-Python: >=3.5
License-File: LICENSE
Provides-Extra: dev
Requires-Dist: pytest >=8.0.1 ; extra == 'dev'
Requires-Dist: pytest-cov >=4.1.0 ; extra == 'dev'
Requires-Dist: pytest-profiling >=1.7.0 ; extra == 'dev'
Requires-Dist: keyring >=24.3.0 ; extra == 'dev'
Requires-Dist: Sphinx >=7.2.0 ; extra == 'dev'
Requires-Dist: setuptools >=69.1.0 ; extra == 'dev'
Requires-Dist: wheel >=0.42.0 ; extra == 'dev'
Requires-Dist: black >=24.0.0 ; extra == 'dev'
Requires-Dist: sphinx-rtd-theme >=2.0.0 ; extra == 'dev'
